{
  "AccommodationService": "TravelService",
  "HotelService": "AccommodationService",
  "LuxuryHotelService": "AccommodationService",
  "BudgetHotelService": "AccommodationService",
  "HostelService": "AccommodationService",
  "ApartmentRentalService": "AccommodationService",
  "VillaRentalService": "AccommodationService",
  "ResortHotelService": "AccommodationService",
  "CampingService": "AccommodationService",
  "ShortTermRentalService": "AccommodationService",
  "FamilyAccommodationService": "AccommodationService",
  "TransportationService": "TravelService",
  "FlightService": "TransportationService",
  "DomesticFlightService": "TransportationService",
  "InternationalFlightService": "TransportationService",
  "TrainService": "TransportationService",
  "BusService": "TransportationService",
  "TaxiService": "TransportationService",
  "AirportTransferService": "TransportationService",
  "CarRentalService": "TransportationService",
  "BikeRentalService": "TransportationService",
  "FerryService": "TransportationService",
  "TourismService": "TravelService",
  "TourGuideService": "TourismService",
  "MuseumRecommendationService": "TourismService",
  "HistoricalPlaceService": "TourismService",
  "CityTourService": "TourismService",
  "EventRecommendationService": "TourismService",
  "RestaurantRecommendationService": "TourismService",
  "AdventureActivityService": "TourismService",
  "CulturalExperienceService": "TourismService",
  "TouristAttractionService": "TourismService",
  "LocalExperienceService": "TourismService",
  "PlanningService": "TravelService",
  "TripPlannerService": "PlanningService",
  "BudgetPlannerService": "PlanningService",
  "RouteOptimizationService": "PlanningService",
  "VacationRecommendationService": "PlanningService",
  "SchedulePlannerService": "PlanningService",
  "ItineraryBuilderService": "PlanningService",
  "GroupTravelPlannerService": "PlanningService",
  "WeekendTripPlannerService": "PlanningService",
  "FamilyTripPlannerService": "PlanningService",
  "BusinessTripPlannerService": "PlanningService",
  "DocumentationService": "TravelService",
  "VisaApplicationService": "DocumentationService",
  "PassportRenewalService": "DocumentationService",
  "EmbassyAppointmentService": "DocumentationService",
  "TravelDocumentVerificationService": "DocumentationService",
  "ElectronicVisaService": "DocumentationService",
  "TravelPermitService": "DocumentationService",
  "DocumentTranslationService": "DocumentationService",
  "ConsularSupportService": "DocumentationService",
  "IdentityVerificationService": "DocumentationService",
  "BorderRequirementService": "DocumentationService",
  "InsuranceAndPaymentService": "TravelService",
  "TravelInsuranceService": "InsuranceAndPaymentService",
  "BookingCancellationService": "InsuranceAndPaymentService",
  "RefundService": "InsuranceAndPaymentService",
  "CurrencyExchangeService": "InsuranceAndPaymentService",
  "InternationalPaymentService": "PaymentService",
  "TravelCardService": "InsuranceAndPaymentService",
  "PaymentInstallmentService": "InsuranceAndPaymentService",
  "PriceComparisonService": "ProductDiscoveryService",
  "SecurePaymentService": "InsuranceAndPaymentService",
  "InvoiceManagementService": "InsuranceAndPaymentService",
  "SafetyAndWeatherService": "TravelService",
  "WeatherForecastService": "SafetyAndWeatherService",
  "EmergencyTravelAlertService": "SafetyAndWeatherService",
  "TravelRiskAssessmentService": "SafetyAndWeatherService",
  "SafeDestinationService": "SafetyAndWeatherService",
  "HealthAdvisoryService": "SafetyAndWeatherService",
  "TravelRestrictionService": "SafetyAndWeatherService",
  "LostItemSupportService": "SafetyAndWeatherService",
  "EmergencyContactService": "SafetyAndWeatherService",
  "NaturalDisasterAlertService": "SafetyAndWeatherService",
  "LocalSafetyGuideService": "SafetyAndWeatherService",
  "ProductDiscoveryService": "EcommerceService",
  "ProductSearchService": "ProductDiscoveryService",
  "ProductRecommendationService": "ProductDiscoveryService",
  "CategoryBrowsingService": "ProductDiscoveryService",
  "ProductReviewService": "ProductDiscoveryService",
  "SimilarProductService": "ProductDiscoveryService",
  "PersonalizedOfferService": "ProductDiscoveryService",
  "NewArrivalService": "ProductDiscoveryService",
  "BestSellerService": "ProductDiscoveryService",
  "WishlistService": "ProductDiscoveryService",
  "OrderManagementService": "EcommerceService",
  "OrderPlacementService": "OrderManagementService",
  "OrderTrackingService": "OrderManagementService",
  "OrderCancellationService": "OrderManagementService",
  "OrderModificationService": "OrderManagementService",
  "InvoiceGenerationService": "OrderManagementService",
  "BulkOrderService": "OrderManagementService",
  "PreOrderService": "OrderManagementService",
  "SubscriptionOrderService": "OrderManagementService",
  "GiftOrderService": "OrderManagementService",
  "OrderHistoryService": "OrderManagementService",
  "PaymentService": "EcommerceService",
  "CreditCardPaymentService": "PaymentService",
  "DigitalWalletPaymentService": "PaymentService",
  "BankTransferService": "PaymentService",
  "InstallmentPaymentService": "PaymentService",
  "CashOnDeliveryService": "PaymentService",
  "PaymentVerificationService": "PaymentService",
  "CouponPaymentService": "PaymentService",
  "RefundPaymentService": "PaymentService",
  "SecureCheckoutService": "PaymentService",
  "DeliveryService": "EcommerceService",
  "StandardDeliveryService": "DeliveryService",
  "ExpressDeliveryService": "DeliveryService",
  "SameDayDeliveryService": "DeliveryService",
  "CargoTrackingService": "DeliveryService",
  "PickupPointService": "DeliveryService",
  "InternationalShippingService": "DeliveryService",
  "DeliverySchedulingService": "DeliveryService",
  "AddressValidationService": "DeliveryService",
  "PackageInsuranceService": "DeliveryService",
  "DeliveryNotificationService": "DeliveryService",
  "ReturnRefundService": "EcommerceService",
  "ReturnRequestService": "ReturnRefundService",
  "RefundRequestService": "ReturnRefundService",
  "ExchangeRequestService": "ReturnRefundService",
  "WarrantyClaimService": "ReturnRefundService",
  "ReturnLabelService": "ReturnRefundService",
  "DefectiveProductService": "ReturnRefundService",
  "CancellationRefundService": "ReturnRefundService",
  "RefundStatusService": "ReturnRefundService",
  "StoreCreditService": "ReturnRefundService",
  "ReturnPolicyService": "ReturnRefundService",
  "CustomerSupportService": "EcommerceService",
  "LiveChatSupportService": "CustomerSupportService",
  "TicketSupportService": "CustomerSupportService",
  "ComplaintManagementService": "CustomerSupportService",
  "FAQRecommendationService": "CustomerSupportService",
  "SellerContactService": "CustomerSupportService",
  "AfterSalesSupportService": "CustomerSupportService",
  "ProductQuestionService": "CustomerSupportService",
  "AccountSupportService": "CustomerSupportService",
  "DisputeResolutionService": "CustomerSupportService",
  "FeedbackCollectionService": "CustomerSupportService",
  "InventoryService": "EcommerceService",
  "StockAvailabilityService": "InventoryService",
  "WarehouseInventoryService": "InventoryService",
  "LowStockAlertService": "InventoryService",
  "RestockNotificationService": "InventoryService",
  "InventoryReservationService": "InventoryService",
  "SupplierStockService": "InventoryService",
  "StoreStockLookupService": "InventoryService",
  "BackorderService": "InventoryService",
  "StockSynchronizationService": "InventoryService",
  "InventoryForecastService": "InventoryService"
}